gimp_mcp_server.py
mseep_gimp_mcp-0.1.3.dist-info/licenses/LICENSE
mseep_gimp_mcp-0.1.3.dist-info/METADATA
mseep_gimp_mcp-0.1.3.dist-info/WHEEL
mseep_gimp_mcp-0.1.3.dist-info/entry_points.txt
mseep_gimp_mcp-0.1.3.dist-info/top_level.txt
mseep_gimp_mcp-0.1.3.dist-info/RECORD
