Metadata-Version: 2.4
Name: mseep-gimp-mcp
Version: 0.1.3
Summary: GIMP MCP integration for external control of GIMP 3.0
Author-email: mseep <support@skydeck.ai>
License:                     GNU GENERAL PUBLIC LICENSE
Requires-Python: >=3.11
License-File: LICENSE
Requires-Dist: mcp
Requires-Dist: fastmcp
Dynamic: license-file
